residue/__init__.py
residue/_version.py
residue/query.py
residue/types.py
residue/crud/__init__.py
residue/crud/api.py
residue/crud/orm.py
residue-0.2.8.dist-info/DESCRIPTION.rst
residue-0.2.8.dist-info/METADATA
residue-0.2.8.dist-info/RECORD
residue-0.2.8.dist-info/WHEEL
residue-0.2.8.dist-info/metadata.json
residue-0.2.8.dist-info/top_level.txt
residue-0.2.8.dist-info/zip-safe
