Metadata-Version: 2.0
Name: residue
Version: 0.2.8
Summary: SQLAlchemy CRUD Utilities
Home-page: http://residue.readthedocs.org
Author: Rob Ruana
Author-email: rob@robruana.com
License: BSD
Download-URL: http://pypi.python.org/pypi/residue
Platform: any
Classifier: Development Status :: 3 - Alpha
Classifier: Environment :: Console
Classifier: Environment :: Web Environment
Classifier: Intended Audience :: Developers
Classifier: License :: OSI Approved :: BSD License
Classifier: Operating System :: OS Independent
Classifier: Programming Language :: Python
Classifier: Programming Language :: Python :: 2
Classifier: Programming Language :: Python :: 3
Classifier: Topic :: Utilities
Classifier: Topic :: Database
Classifier: Topic :: Software Development :: Libraries
Classifier: Topic :: Software Development :: Libraries :: Application Frameworks
Classifier: Topic :: Software Development :: Libraries :: Python Modules
Requires-Dist: backports.functools-lru-cache (>=1.3)
Requires-Dist: pockets (>=0.6.1)
Requires-Dist: pytz (>=2017.2)
Requires-Dist: six (>=1.5.2)
Requires-Dist: SQLAlchemy (>=1.0.0)
